sgneskig/__init__.py
sgneskig/_version.py
sgneskig/pipeline.py
sgneskig/bin/__init__.py
sgneskig/bin/grafana_datasource.py
sgneskig/bin/grafana_import.py
sgneskig/metrics/__init__.py
sgneskig/metrics/collector.py
sgneskig/metrics/grafana.py
sgneskig/metrics/writer.py
sgneskig/sinks/__init__.py
sgneskig/sinks/kafka_sink.py
sgneskig/sinks/scald_metrics_sink.py
sgneskig/sources/__init__.py
sgneskig/sources/kafka_source.py
sgneskig/transforms/__init__.py
sgneskig/transforms/delay_buffer.py
sgneskig/transforms/event_latency.py
sgneskig/transforms/round_robin_distributor.py
sgn_skig-0.1.0.dist-info/METADATA
sgn_skig-0.1.0.dist-info/WHEEL
sgn_skig-0.1.0.dist-info/entry_points.txt
sgn_skig-0.1.0.dist-info/top_level.txt
sgn_skig-0.1.0.dist-info/RECORD
