Metadata-Version: 2.4
Name: sgn-skig
Version: 0.1.0
Summary: SGN infrastructure for metrics, Kafka, InfluxDB, and Grafana integration
Author-email: Chad Hanna <crh184@psu.edu>
License: MPL-2.0
Requires-Python: >=3.11
Requires-Dist: sgn>=0.5
Requires-Dist: confluent-kafka>=2.0
Requires-Dist: ligo-scald
Requires-Dist: pyyaml
Requires-Dist: requests
Provides-Extra: test
Requires-Dist: pytest; extra == "test"
Requires-Dist: pytest-cov; extra == "test"
Requires-Dist: pytest-asyncio; extra == "test"
Provides-Extra: lint
Requires-Dist: ruff; extra == "lint"
Provides-Extra: dev
Requires-Dist: sgn-skig[lint,test]; extra == "dev"
